.DS_Store
proto/__init__.py
proto/speech2text_pb2.py
proto/speech2text_pb2_grpc.py
utils/__init__.py
utils/check_mic.py
utils/stream_output.py
bnasr-0.1.11.dist-info/METADATA
bnasr-0.1.11.dist-info/WHEEL
bnasr-0.1.11.dist-info/top_level.txt
bnasr-0.1.11.dist-info/RECORD
